control/__init__.py
control/controller.py
control/ssh.py
clossh_MetallicSquid-0.1.1.dist-info/LICENSE
clossh_MetallicSquid-0.1.1.dist-info/METADATA
clossh_MetallicSquid-0.1.1.dist-info/WHEEL
clossh_MetallicSquid-0.1.1.dist-info/top_level.txt
clossh_MetallicSquid-0.1.1.dist-info/RECORD
